my_cli_tool/__init__.py
my_cli_tool/cli.py
my_cli_tool-0.4.dist-info/METADATA
my_cli_tool-0.4.dist-info/WHEEL
my_cli_tool-0.4.dist-info/entry_points.txt
my_cli_tool-0.4.dist-info/top_level.txt
my_cli_tool-0.4.dist-info/RECORD
