Metadata-Version: 2.1
Name: my-cli-tool
Version: 0.4
Summary: A simple CLI tool to add two numbers.
Home-page: https://github.com/yourusername/my_cli_tool
Author: Your Name
Author-email: your.email@example.com
License: UNKNOWN
Platform: UNKNOWN
Classifier: Programming Language :: Python :: 3
Classifier: License :: OSI Approved :: MIT License
Classifier: Operating System :: OS Independent
Requires-Python: >=3.6
